sensirion_driver_support_types/__init__.py
sensirion_driver_support_types/bitfield.py
sensirion_driver_support_types/cstruct_template.py
sensirion_driver_support_types/mixin_access.py
sensirion_driver_support_types/py_legacy.py
sensirion_driver_support_types/signals.py
sensirion_driver_support_types/version.py
sensirion_driver_support_types-1.2.0.dist-info/LICENSE
sensirion_driver_support_types-1.2.0.dist-info/METADATA
sensirion_driver_support_types-1.2.0.dist-info/WHEEL
sensirion_driver_support_types-1.2.0.dist-info/top_level.txt
sensirion_driver_support_types-1.2.0.dist-info/RECORD
